setup.py
easyGuiCover/__init__.py
easyGuiCover/easyGuiCover.py
easyGuiCover.egg-info/PKG-INFO
easyGuiCover.egg-info/SOURCES.txt
easyGuiCover.egg-info/dependency_links.txt
easyGuiCover.egg-info/top_level.txt