Metadata-Version: 2.1
Name: easyGuiCover
Version: 0.0.1
Summary: This is easy library to open explorer on top of other screens!
Author: Luka
Author-email: app6onpython@gmail.com
Keywords: easyGuiCover,Cover,easyguicover,easygui,gui,easy,Easygui,Gui,Easy,cover
Classifier: Programming Language :: Python :: 3.9
